Workbook
Name Total_Monthly_Expenses: #REF!
Name Total_Monthly_Income: #REF!
Name Total_Monthly_Savings: #REF!
Name TotalMonthlyExpenses: #REF!
Name TotalMonthlyIncome: #REF!
Name TotalMonthlySavings: #REF!

Sheet Jan
A1: January 20XX
A2: Expenses | K2: Income
A3: Fixed | D3: Flexible | G3: Discretionary | K3: Work | N3: Other
A4: Date | B4: Source | C4: Cost | D4: Date | E4: Source | F4: Cost | G4: Date | H4: Source | I4: Cost | K4: Date | L4: Source | M4: Amount | N4: Date | O4: Source | P4: Amount
A5: 45660 | B5: Rent | C5: 5000 | D5: 45658 | E5: Groceries | F5: 100 | G5: 45667 | H5: Night Out | I5: 80 | K5: 45658 | L5: Paycheck | M5: 15000 | N5: 45661 | O5: Venmo Payment | P5: 10
D6: 45669 | E6: Gas | F6: 35
A13: Total | C13: =SUM(C5:C12) -> 5000 | D13: Total | F13: =SUM(F5:F12) -> 135 | G13: Total | I13: =SUBTOTAL(109,Jan!$I$5:$I$12) -> 80 | K13: Total | M13: =SUM(M5:M12) -> 15000 | N13: Total | P13: =SUM(P5:P12) -> 10
A15: Beg. Bal | B15: =0 -> 0 | O15: End Bal. | P15: =B15+(M13+P13)-(C13+F13+I13) -> 9795
A17: Amount Earned | B17: =M13+P13 -> 15010
A18: Amount Spent | B18: =C13+F13+I13 -> 5215
A19: Remaining | B19: =B17-B18 -> 9795

Sheet Feb
A1: February 20XX
A2: Expenses | K2: Income
A3: Fixed | D3: Flexible | G3: Discretionary | K3: Work | N3: Other
A4: Date | B4: Source | C4: Cost | D4: Date | E4: Source | F4: Cost | G4: Date | H4: Source | I4: Cost | K4: Date | L4: Source | M4: Amount | N4: Date | O4: Source | P4: Amount
A22: Total | C22: =SUM(C5:C21) -> 0 | D22: Total | F22: =SUM(F5:F21) -> 0 | G22: Total | I22: =SUBTOTAL(109,Feb!$I$5:$I$21) -> 0 | K22: Total | M22: =SUM(M5:M21) -> 0 | N22: Total | P22: =SUM(P5:P21) -> 0
A24: Beg. Bal | B24: =0 -> 0 | O24: End Bal. | P24: =B24+(M22+P22)-(C22+F22+I22) -> 0
A26: Amount Earned | B26: =M22+P22 -> 0
A27: Amount Spent | B27: =C22+F22+I22 -> 0
A28: Remaining | B28: =B26-B27 -> 0

Sheet Mar
A1: March 20XX
A2: Expenses | K2: Income
A3: Fixed | D3: Flexible | G3: Discretionary | K3: Work | N3: Other
A4: Date | B4: Source | C4: Cost | D4: Date | E4: Source | F4: Cost | G4: Date | H4: Source | I4: Cost | K4: Date | L4: Source | M4: Amount | N4: Date | O4: Source | P4: Amount
A22: Total | C22: =SUM(C5:C21) -> 0 | D22: Total | F22: =SUM(F5:F21) -> 0 | G22: Total | I22: =SUBTOTAL(109,Mar!$I$5:$I$21) -> 0 | K22: Total | M22: =SUM(M5:M21) -> 0 | N22: Total | P22: =SUM(P5:P21) -> 0
A24: Beg. Bal | B24: =0 -> 0 | O24: End Bal. | P24: =B24+(M22+P22)-(C22+F22+I22) -> 0
A26: Amount Earned | B26: =M22+P22 -> 0
A27: Amount Spent | B27: =C22+F22+I22 -> 0
A28: Remaining | B28: =B26-B27 -> 0

Sheet April
A1: April 20XX
A2: Expenses | K2: Income
A3: Fixed | D3: Flexible | G3: Discretionary | K3: Work | N3: Other
A4: Date | B4: Source | C4: Cost | D4: Date | E4: Source | F4: Cost | G4: Date | H4: Source | I4: Cost | K4: Date | L4: Source | M4: Amount | N4: Date | O4: Source | P4: Amount
A22: Total | C22: =SUM(C5:C21) -> 0 | D22: Total | F22: =SUM(F5:F21) -> 0 | G22: Total | I22: =SUBTOTAL(109,April!$I$5:$I$21) -> 0 | K22: Total | M22: =SUM(M5:M21) -> 0 | N22: Total | P22: =SUM(P5:P21) -> 0
A24: Beg. Bal | B24: =0 -> 0 | O24: End Bal. | P24: =B24+(M22+P22)-(C22+F22+I22) -> 0
A26: Amount Earned | B26: =M22+P22 -> 0
A27: Amount Spent | B27: =C22+F22+I22 -> 0
A28: Remaining | B28: =B26-B27 -> 0

Sheet May
A1: May 20XX
A2: Expenses | K2: Income
A3: Fixed | D3: Flexible | G3: Discretionary | K3: Work | N3: Other
A4: Date | B4: Source | C4: Cost | D4: Date | E4: Source | F4: Cost | G4: Date | H4: Source | I4: Cost | K4: Date | L4: Source | M4: Amount | N4: Date | O4: Source | P4: Amount
A22: Total | C22: =SUM(C5:C21) -> 0 | D22: Total | F22: =SUM(F5:F21) -> 0 | G22: Total | I22: =SUBTOTAL(109,May!$I$5:$I$21) -> 0 | K22: Total | M22: =SUM(M5:M21) -> 0 | N22: Total | P22: =SUM(P5:P21) -> 0
A24: Beg. Bal | B24: =0 -> 0 | O24: End Bal. | P24: =B24+(M22+P22)-(C22+F22+I22) -> 0
A26: Amount Earned | B26: =M22+P22 -> 0
A27: Amount Spent | B27: =C22+F22+I22 -> 0
A28: Remaining | B28: =B26-B27 -> 0

Sheet Jun
A1: June 20XX
A2: Expenses | K2: Income
A3: Fixed | D3: Flexible | G3: Discretionary | K3: Work | N3: Other
A4: Date | B4: Source | C4: Cost | D4: Date | E4: Source | F4: Cost | G4: Date | H4: Source | I4: Cost | K4: Date | L4: Source | M4: Amount | N4: Date | O4: Source | P4: Amount
A22: Total | C22: =SUM(C5:C21) -> 0 | D22: Total | F22: =SUM(F5:F21) -> 0 | G22: Total | I22: =SUBTOTAL(109,Jun!$I$5:$I$21) -> 0 | K22: Total | M22: =SUM(M5:M21) -> 0 | N22: Total | P22: =SUM(P5:P21) -> 0
A24: Beg. Bal | B24: =0 -> 0 | O24: End Bal. | P24: =B24+(M22+P22)-(C22+F22+I22) -> 0
A26: Amount Earned | B26: =M22+P22 -> 0
A27: Amount Spent | B27: =C22+F22+I22 -> 0
A28: Remaining | B28: =B26-B27 -> 0

Sheet Jul
A1: July 20XX
A2: Expenses | K2: Income
A3: Fixed | D3: Flexible | G3: Discretionary | K3: Work | N3: Other
A4: Date | B4: Source | C4: Cost | D4: Date | E4: Source | F4: Cost | G4: Date | H4: Source | I4: Cost | K4: Date | L4: Source | M4: Amount | N4: Date | O4: Source | P4: Amount
A22: Total | C22: =SUM(C5:C21) -> 0 | D22: Total | F22: =SUM(F5:F21) -> 0 | G22: Total | I22: =SUBTOTAL(109,Jul!$I$5:$I$21) -> 0 | K22: Total | M22: =SUM(M5:M21) -> 0 | N22: Total | P22: =SUM(P5:P21) -> 0
A24: Beg. Bal | B24: =0 -> 0 | O24: End Bal. | P24: =B24+(M22+P22)-(C22+F22+I22) -> 0
A26: Amount Earned | B26: =M22+P22 -> 0
A27: Amount Spent | B27: =C22+F22+I22 -> 0
A28: Remaining | B28: =B26-B27 -> 0

Sheet Aug
A1: August 20XX
A2: Expenses | K2: Income
A3: Fixed | D3: Flexible | G3: Discretionary | K3: Work | N3: Other
A4: Date | B4: Source | C4: Cost | D4: Date | E4: Source | F4: Cost | G4: Date | H4: Source | I4: Cost | K4: Date | L4: Source | M4: Amount | N4: Date | O4: Source | P4: Amount
A22: Total | C22: =SUM(C5:C21) -> 0 | D22: Total | F22: =SUM(F5:F21) -> 0 | G22: Total | I22: =SUBTOTAL(109,Aug!$I$5:$I$21) -> 0 | K22: Total | M22: =SUM(M5:M21) -> 0 | N22: Total | P22: =SUM(P5:P21) -> 0
A24: Beg. Bal | B24: =0 -> 0 | O24: End Bal. | P24: =B24+(M22+P22)-(C22+F22+I22) -> 0
A26: Amount Earned | B26: =M22+P22 -> 0
A27: Amount Spent | B27: =C22+F22+I22 -> 0
A28: Remaining | B28: =B26-B27 -> 0

Sheet Sep
A1: September 20XX
A2: Expenses | K2: Income
A3: Fixed | D3: Flexible | G3: Discretionary | K3: Work | N3: Other
A4: Date | B4: Source | C4: Cost | D4: Date | E4: Source | F4: Cost | G4: Date | H4: Source | I4: Cost | K4: Date | L4: Source | M4: Amount | N4: Date | O4: Source | P4: Amount
A22: Total | C22: =SUM(C5:C21) -> 0 | D22: Total | F22: =SUM(F5:F21) -> 0 | G22: Total | I22: =SUBTOTAL(109,Sep!$I$5:$I$21) -> 0 | K22: Total | M22: =SUM(M5:M21) -> 0 | N22: Total | P22: =SUM(P5:P21) -> 0
A24: Beg. Bal | B24: =0 -> 0 | O24: End Bal. | P24: =B24+(M22+P22)-(C22+F22+I22) -> 0
A26: Amount Earned | B26: =M22+P22 -> 0
A27: Amount Spent | B27: =C22+F22+I22 -> 0
A28: Remaining | B28: =B26-B27 -> 0

Sheet Oct
A1: October 20XX
A2: Expenses | K2: Income
A3: Fixed | D3: Flexible | G3: Discretionary | K3: Work | N3: Other
A4: Date | B4: Source | C4: Cost | D4: Date | E4: Source | F4: Cost | G4: Date | H4: Source | I4: Cost | K4: Date | L4: Source | M4: Amount | N4: Date | O4: Source | P4: Amount
A22: Total | C22: =SUM(C5:C21) -> 0 | D22: Total | F22: =SUM(F5:F21) -> 0 | G22: Total | I22: =SUBTOTAL(109,Oct!$I$5:$I$21) -> 0 | K22: Total | M22: =SUM(M5:M21) -> 0 | N22: Total | P22: =SUM(P5:P21) -> 0
A24: Beg. Bal | B24: =0 -> 0 | O24: End Bal. | P24: =B24+(M22+P22)-(C22+F22+I22) -> 0
A26: Amount Earned | B26: =M22+P22 -> 0
A27: Amount Spent | B27: =C22+F22+I22 -> 0
A28: Remaining | B28: =B26-B27 -> 0

Sheet Nov
A1: November 20XX
A2: Expenses | K2: Income
A3: Fixed | D3: Flexible | G3: Discretionary | K3: Work | N3: Other
A4: Date | B4: Source | C4: Cost | D4: Date | E4: Source | F4: Cost | G4: Date | H4: Source | I4: Cost | K4: Date | L4: Source | M4: Amount | N4: Date | O4: Source | P4: Amount
A22: Total | C22: =SUM(C5:C21) -> 0 | D22: Total | F22: =SUM(F5:F21) -> 0 | G22: Total | I22: =SUBTOTAL(109,Nov!$I$5:$I$21) -> 0 | K22: Total | M22: =SUM(M5:M21) -> 0 | N22: Total | P22: =SUM(P5:P21) -> 0
A24: Beg. Bal | B24: =0 -> 0 | O24: End Bal. | P24: =B24+(M22+P22)-(C22+F22+I22) -> 0
A26: Amount Earned | B26: =M22+P22 -> 0
A27: Amount Spent | B27: =C22+F22+I22 -> 0
A28: Remaining | B28: =B26-B27 -> 0

Sheet Dec
A1: December 20XX
A2: Expenses | K2: Income
A3: Fixed | D3: Flexible | G3: Discretionary | K3: Work | N3: Other
A4: Date | B4: Source | C4: Cost | D4: Date | E4: Source | F4: Cost | G4: Date | H4: Source | I4: Cost | K4: Date | L4: Source | M4: Amount | N4: Date | O4: Source | P4: Amount
A22: Total | C22: =SUM(C5:C21) -> 0 | D22: Total | F22: =SUM(F5:F21) -> 0 | G22: Total | I22: =SUBTOTAL(109,Dec!$I$5:$I$21) -> 0 | K22: Total | M22: =SUM(M5:M21) -> 0 | N22: Total | P22: =SUM(P5:P21) -> 0
A24: Beg. Bal | B24: =0 -> 0 | O24: End Bal. | P24: =B24+(M22+P22)-(C22+F22+I22) -> 0
A26: Amount Earned | B26: =M22+P22 -> 0
A27: Amount Spent | B27: =C22+F22+I22 -> 0
A28: Remaining | B28: =B26-B27 -> 0

Sheet Totals
A1: Total Income
A2: 20XX Totals
A3: Income | B3: January | C3: February | D3: March | E3: April | F3: May | G3: June | H3: July | I3: August | J3: September | K3: October | L3: November | M3: December | N3: Total
A4: Work | B4: =Jan!M13 -> 15000 | C4: =Feb!M22 -> 0 | D4: =Mar!M22 -> 0 | E4: =April!M22 -> 0 | F4: =May!M22 -> 0 | G4: =Jun!M22 -> 0 | H4: =Jul!M22 -> 0 | I4: =Aug!M22 -> 0 | J4: =Sep!M22 -> 0 | K4: =Oct!M22 -> 0 | L4: =Nov!M22 -> 0 | M4: =Dec!M22 -> 0 | N4: =SUM(B4:M4) -> 15000
A5: Other | B5: =Jan!P13 -> 10 | C5: =Feb!P22 -> 0 | D5: =Mar!P22 -> 0 | E5: =April!P22 -> 0 | F5: =May!P22 -> 0 | G5: =Jun!P22 -> 0 | H5: =Jul!P22 -> 0 | I5: =Aug!P22 -> 0 | J5: =Sep!P22 -> 0 | K5: =Oct!P22 -> 0 | L5: =Nov!P22 -> 0 | M5: =Dec!P22 -> 0 | N5: =SUM(B5:M5) -> 10
A6: Total | B6: =SUM(B4:B5) -> 15010 | C6: =SUM(C4:C5) -> 0 | D6: =SUM(D4:D5) -> 0 | E6: =SUM(E4:E5) -> 0 | F6: =SUM(F4:F5) -> 0 | G6: =SUM(G4:G5) -> 0 | H6: =SUM(H4:H5) -> 0 | I6: =SUM(I4:I5) -> 0 | ... M6: =SUM(M4:M5) -> 0 | N6: =SUM(B6:M6) -> 15010
A8: Expenses | B8: =B3 -> January | C8: =C3 -> February | D8: =D3 -> March | E8: =E3 -> April | F8: =F3 -> May | G8: =G3 -> June | H8: =H3 -> July | I8: =I3 -> August | ... M8: =M3 -> December | N8: Total
A9: Fixed Expenses | B9: =Jan!C13 -> 5000 | C9: =Feb!C22 -> 0 | D9: =Mar!C22 -> 0 | E9: =April!C22 -> 0 | F9: =May!C22 -> 0 | G9: =Jun!C22 -> 0 | H9: =Jul!C22 -> 0 | I9: =Aug!C22 -> 0 | J9: =Sep!C22 -> 0 | K9: =Oct!C22 -> 0 | L9: =Nov!C22 -> 0 | M9: =Dec!C22 -> 0 | N9: =SUM(B9:M9) -> 5000
A10: Flexible Expenses | B10: =Jan!F13 -> 135 | C10: =Feb!F22 -> 0 | D10: =Mar!F22 -> 0 | E10: =April!F22 -> 0 | F10: =May!F22 -> 0 | G10: =Jun!F22 -> 0 | H10: =Jul!F22 -> 0 | I10: =Aug!F22 -> 0 | J10: =Sep!F22 -> 0 | K10: =Oct!F22 -> 0 | L10: =Nov!F22 -> 0 | M10: =Dec!F22 -> 0 | N10: =SUM(B10:M10) -> 135
A11: Discretionary Expenses | B11: =Jan!I13 -> 80 | C11: =Feb!I22 -> 0 | D11: =Mar!I22 -> 0 | E11: =April!I22 -> 0 | F11: =May!I22 -> 0 | G11: =Jun!I22 -> 0 | H11: =Jul!I22 -> 0 | I11: =Aug!I22 -> 0 | J11: =Sep!I22 -> 0 | K11: =Oct!I22 -> 0 | L11: =Nov!I22 -> 0 | M11: =Dec!I22 -> 0 | N11: =SUM(B11:M11) -> 80
A12: Total | B12: =SUM(B9:B11) -> 5215 | C12: =SUM(C9:C11) -> 0 | D12: =SUM(D9:D11) -> 0 | E12: =SUM(E9:E11) -> 0 | F12: =SUM(F9:F11) -> 0 | G12: =SUM(G9:G11) -> 0 | H12: =SUM(H9:H11) -> 0 | I12: =SUM(I9:I11) -> 0 | ... N12: =SUM(N9:N11) -> 5215
A14: Net | B14: =B6-B12 -> 9795 | C14: =C6-C12 -> 0 | D14: =D6-D12 -> 0 | E14: =E6-E12 -> 0 | F14: =F6-F12 -> 0 | G14: =G6-G12 -> 0 | H14: =H6-H12 -> 0 | I14: =I6-I12 -> 0 | ... N14: =N6-N12 -> 9795

Sheet Chart Data
B2: CHART DATA
B4: =MIN(1-B5,1) -> #REF!
B5: =MIN(Total_Monthly_Expenses/Total_Monthly_Income,1) -> #REF!
B6: =(Total_Monthly_Expenses/Total_Monthly_Income)>1 -> #REF!
