Workbook
Name Total_Monthly_Expenses: #REF!
Name Total_Monthly_Income: #REF!
Name Total_Monthly_Savings: #REF!
Name TotalMonthlyExpenses: #REF!
Name TotalMonthlyIncome: #REF!
Name TotalMonthlySavings: #REF!

Sheet Jan
A1: January
A2: Expenses | N2: Income
A3: Fixed | E3: Flexible | I3: Discretionary | N3: Work | Q3: Other
A4: Date | B4: Source | C4: Category | D4: Cost | E4: Date | F4: Source | G4: Category | H4: Cost | I4: Date | J4: Source | K4: Category | L4: Cost | N4: Date | O4: Source | P4: Amount | Q4: Date | R4: Source | S4: Amount
A5: 46023 | B5: NYC Real Estate | C5: Rent | D5: 4000 | E5: 46027 | F5: Trader Joe's | G5: Groceries | H5: 25 | I5: 46032 | J5: Noi Due | K5: Eating Out | L5: 45 | N5: 46026 | O5: Paycheck | P5: 5000 | Q5: 46024 | R5: Venmo from Friend | S5: 15
A6: 46023 | B6: Verizon | C6: Wifi | D6: 50 | E6: 46029 | F6: Sunoco | G6: Gas | H6: 45
E7: 46037 | F7: Con Edison | G7: Utilities | H7: 200
A35: Total | D35: =SUM(D5:D34) -> 4050 | E35: Total | H35: =SUM(H5:H34) -> 270 | I35: Total | L35: =SUBTOTAL(109,Jan!$L$5:$L$34) -> 45 | N35: Total | P35: =SUM(P5:P34) -> 5000 | Q35: Total | S35: =SUM(S5:S34) -> 15
A37: Beg. Bal | C37: 0 | R37: End Bal. | S37: =C37+(P35+S35)-(D35+H35+L35) -> 650
A39: Amount Earned | B39: =P35+S35 -> 5015 | O39: Public Transit | P39: Price | Q39: # Rides | R39: Cost
A40: Amount Spent | B40: =D35+H35+L35 -> 4365 | O40: Subway/Bus | P40: 3 | Q40: 0 | R40: =P40*Q40 -> 0
A41: Remaining | B41: =B39-B40 -> 650 | O41: NJT | P41: 5.45 | Q41: 0 | R41: =P41*Q41 -> 0
O42: Jitney | P42: 3.5 | Q42: 0 | R42: =P42*Q42 -> 0
O43: Total | Q43: =SUBTOTAL(109,Q40:Q42) -> 0 | R43: =SUM(R40:R42) -> 0

Sheet Feb
A1: February
A2: Expenses | N2: Income
A3: Fixed | E3: Flexible | I3: Discretionary | N3: Work | Q3: Other
A4: Date | B4: Source | C4: Category | D4: Cost | E4: Date | F4: Source | G4: Category | H4: Cost | I4: Date | J4: Source | K4: Category | L4: Cost | N4: Date | O4: Source | P4: Amount | Q4: Date | R4: Source | S4: Amount
A35: Total | D35: =SUM(D5:D34) -> 0 | E35: Total | H35: =SUM(H5:H34) -> 0 | I35: Total | L35: =SUBTOTAL(109,Feb!$L$5:$L$34) -> 0 | N35: Total | P35: =SUM(P5:P34) -> 0 | Q35: Total | S35: =SUM(S5:S34) -> 0
A37: Beg. Bal | C37: =Jan!S37 -> 650 | R37: End Bal. | S37: =C37+(P35+S35)-(D35+H35+L35) -> 650
A39: Amount Earned | B39: =P35+S35 -> 0 | O39: Public Transit | P39: Price | Q39: # Rides | R39: Cost
A40: Amount Spent | B40: =D35+H35+L35 -> 0 | O40: Subway/Bus | P40: 3 | Q40: 0 | R40: =P40*Q40 -> 0
A41: Remaining | B41: =B39-B40 -> 0 | O41: NJT | P41: 5.45 | Q41: 0 | R41: =P41*Q41 -> 0
O42: Jitney | P42: 3.5 | Q42: 0 | R42: =P42*Q42 -> 0
O43: Total | Q43: =SUBTOTAL(109,Q40:Q42) -> 0 | R43: =SUM(R40:R42) -> 0

Sheet Mar
A1: March
A2: Expenses | N2: Income
A3: Fixed | E3: Flexible | I3: Discretionary | N3: Work | Q3: Other
A4: Date | B4: Source | C4: Category | D4: Cost | E4: Date | F4: Source | G4: Category | H4: Cost | I4: Date | J4: Source | K4: Category | L4: Cost | N4: Date | O4: Source | P4: Amount | Q4: Date | R4: Source | S4: Amount
A35: Total | D35: =SUM(D5:D34) -> 0 | E35: Total | H35: =SUM(H5:H34) -> 0 | I35: Total | L35: =SUBTOTAL(109,Mar!$L$5:$L$34) -> 0 | N35: Total | P35: =SUM(P5:P34) -> 0 | Q35: Total | S35: =SUM(S5:S34) -> 0
A37: Beg. Bal | C37: =Feb!S37 -> 650 | R37: End Bal. | S37: =C37+(P35+S35)-(D35+H35+L35) -> 650
A39: Amount Earned | B39: =P35+S35 -> 0 | O39: Public Transit | P39: Price | Q39: # Rides | R39: Cost
A40: Amount Spent | B40: =D35+H35+L35 -> 0 | O40: Subway/Bus | P40: 3 | Q40: 0 | R40: =P40*Q40 -> 0
A41: Remaining | B41: =B39-B40 -> 0 | O41: NJT | P41: 5.45 | Q41: 0 | R41: =P41*Q41 -> 0
O42: Jitney | P42: 3.5 | Q42: 0 | R42: =P42*Q42 -> 0
O43: Total | Q43: =SUBTOTAL(109,Q40:Q42) -> 0 | R43: =SUM(R40:R42) -> 0

Sheet Apr
A1: April
A2: Expenses | N2: Income
A3: Fixed | E3: Flexible | I3: Discretionary | N3: Work | Q3: Other
A4: Date | B4: Source | C4: Category | D4: Cost | E4: Date | F4: Source | G4: Category | H4: Cost | I4: Date | J4: Source | K4: Category | L4: Cost | N4: Date | O4: Source | P4: Amount | Q4: Date | R4: Source | S4: Amount
A35: Total | D35: =SUM(D5:D34) -> 0 | E35: Total | H35: =SUM(H5:H34) -> 0 | I35: Total | L35: =SUBTOTAL(109,Apr!$L$5:$L$34) -> 0 | N35: Total | P35: =SUM(P5:P34) -> 0 | Q35: Total | S35: =SUM(S5:S34) -> 0
A37: Beg. Bal | C37: =Mar!S37 -> 650 | R37: End Bal. | S37: =C37+(P35+S35)-(D35+H35+L35) -> 650
A39: Amount Earned | B39: =P35+S35 -> 0 | O39: Public Transit | P39: Price | Q39: # Rides | R39: Cost
A40: Amount Spent | B40: =D35+H35+L35 -> 0 | O40: Subway/Bus | P40: 3 | Q40: 0 | R40: =P40*Q40 -> 0
A41: Remaining | B41: =B39-B40 -> 0 | O41: NJT | P41: 5.45 | Q41: 0 | R41: =P41*Q41 -> 0
O42: Jitney | P42: 3.5 | Q42: 0 | R42: =P42*Q42 -> 0
O43: Total | Q43: =SUBTOTAL(109,Q40:Q42) -> 0 | R43: =SUM(R40:R42) -> 0

Sheet May
A1: May
A2: Expenses | N2: Income
A3: Fixed | E3: Flexible | I3: Discretionary | N3: Work | Q3: Other
A4: Date | B4: Source | C4: Category | D4: Cost | E4: Date | F4: Source | G4: Category | H4: Cost | I4: Date | J4: Source | K4: Category | L4: Cost | N4: Date | O4: Source | P4: Amount | Q4: Date | R4: Source | S4: Amount
A35: Total | D35: =SUM(D5:D34) -> 0 | E35: Total | H35: =SUM(H5:H34) -> 0 | I35: Total | L35: =SUBTOTAL(109,May!$L$5:$L$34) -> 0 | N35: Total | P35: =SUM(P5:P34) -> 0 | Q35: Total | S35: =SUM(S5:S34) -> 0
A37: Beg. Bal | C37: =Apr!S37 -> 650 | R37: End Bal. | S37: =C37+(P35+S35)-(D35+H35+L35) -> 650
A39: Amount Earned | B39: =P35+S35 -> 0 | O39: Public Transit | P39: Price | Q39: # Rides | R39: Cost
A40: Amount Spent | B40: =D35+H35+L35 -> 0 | O40: Subway/Bus | P40: 3 | Q40: 0 | R40: =P40*Q40 -> 0
A41: Remaining | B41: =B39-B40 -> 0 | O41: NJT | P41: 5.45 | Q41: 0 | R41: =P41*Q41 -> 0
O42: Jitney | P42: 3.5 | Q42: 0 | R42: =P42*Q42 -> 0
O43: Total | Q43: =SUBTOTAL(109,Q40:Q42) -> 0 | R43: =SUM(R40:R42) -> 0

Sheet Jun
A1: June
A2: Expenses | N2: Income
A3: Fixed | E3: Flexible | I3: Discretionary | N3: Work | Q3: Other
A4: Date | B4: Source | C4: Category | D4: Cost | E4: Date | F4: Source | G4: Category | H4: Cost | I4: Date | J4: Source | K4: Category | L4: Cost | N4: Date | O4: Source | P4: Amount | Q4: Date | R4: Source | S4: Amount
A35: Total | D35: =SUM(D5:D34) -> 0 | E35: Total | H35: =SUM(H5:H34) -> 0 | I35: Total | L35: =SUBTOTAL(109,Jun!$L$5:$L$34) -> 0 | N35: Total | P35: =SUM(P5:P34) -> 0 | Q35: Total | S35: =SUM(S5:S34) -> 0
A37: Beg. Bal | C37: =May!S37 -> 650 | R37: End Bal. | S37: =C37+(P35+S35)-(D35+H35+L35) -> 650
A39: Amount Earned | B39: =P35+S35 -> 0 | O39: Public Transit | P39: Price | Q39: # Rides | R39: Cost
A40: Amount Spent | B40: =D35+H35+L35 -> 0 | O40: Subway/Bus | P40: 3 | Q40: 0 | R40: =P40*Q40 -> 0
A41: Remaining | B41: =B39-B40 -> 0 | O41: NJT | P41: 5.45 | Q41: 0 | R41: =P41*Q41 -> 0
O42: Jitney | P42: 3.5 | Q42: 0 | R42: =P42*Q42 -> 0
O43: Total | Q43: =SUBTOTAL(109,Q40:Q42) -> 0 | R43: =SUM(R40:R42) -> 0

Sheet Jul
A1: July
A2: Expenses | N2: Income
A3: Fixed | E3: Flexible | I3: Discretionary | N3: Work | Q3: Other
A4: Date | B4: Source | C4: Category | D4: Cost | E4: Date | F4: Source | G4: Category | H4: Cost | I4: Date | J4: Source | K4: Category | L4: Cost | N4: Date | O4: Source | P4: Amount | Q4: Date | R4: Source | S4: Amount
A35: Total | D35: =SUM(D5:D34) -> 0 | E35: Total | H35: =SUM(H5:H34) -> 0 | I35: Total | L35: =SUBTOTAL(109,Jul!$L$5:$L$34) -> 0 | N35: Total | P35: =SUM(P5:P34) -> 0 | Q35: Total | S35: =SUM(S5:S34) -> 0
A37: Beg. Bal | C37: =Jun!S37 -> 650 | R37: End Bal. | S37: =C37+(P35+S35)-(D35+H35+L35) -> 650
A39: Amount Earned | B39: =P35+S35 -> 0 | O39: Public Transit | P39: Price | Q39: # Rides | R39: Cost
A40: Amount Spent | B40: =D35+H35+L35 -> 0 | O40: Subway/Bus | P40: 3 | Q40: 0 | R40: =P40*Q40 -> 0
A41: Remaining | B41: =B39-B40 -> 0 | O41: NJT | P41: 5.45 | Q41: 0 | R41: =P41*Q41 -> 0
O42: Jitney | P42: 3.5 | Q42: 0 | R42: =P42*Q42 -> 0
O43: Total | Q43: =SUBTOTAL(109,Q40:Q42) -> 0 | R43: =SUM(R40:R42) -> 0

Sheet Aug
A1: August
A2: Expenses | N2: Income
A3: Fixed | E3: Flexible | I3: Discretionary | N3: Work | Q3: Other
A4: Date | B4: Source | C4: Category | D4: Cost | E4: Date | F4: Source | G4: Category | H4: Cost | I4: Date | J4: Source | K4: Category | L4: Cost | N4: Date | O4: Source | P4: Amount | Q4: Date | R4: Source | S4: Amount
A35: Total | D35: =SUM(D5:D34) -> 0 | E35: Total | H35: =SUM(H5:H34) -> 0 | I35: Total | L35: =SUBTOTAL(109,Aug!$L$5:$L$34) -> 0 | N35: Total | P35: =SUM(P5:P34) -> 0 | Q35: Total | S35: =SUM(S5:S34) -> 0
A37: Beg. Bal | C37: =Jul!S37 -> 650 | R37: End Bal. | S37: =C37+(P35+S35)-(D35+H35+L35) -> 650
A39: Amount Earned | B39: =P35+S35 -> 0 | O39: Public Transit | P39: Price | Q39: # Rides | R39: Cost
A40: Amount Spent | B40: =D35+H35+L35 -> 0 | O40: Subway/Bus | P40: 3 | Q40: 0 | R40: =P40*Q40 -> 0
A41: Remaining | B41: =B39-B40 -> 0 | O41: NJT | P41: 5.45 | Q41: 0 | R41: =P41*Q41 -> 0
O42: Jitney | P42: 3.5 | Q42: 0 | R42: =P42*Q42 -> 0
O43: Total | Q43: =SUBTOTAL(109,Q40:Q42) -> 0 | R43: =SUM(R40:R42) -> 0

Sheet Sep
A1: September
A2: Expenses | N2: Income
A3: Fixed | E3: Flexible | I3: Discretionary | N3: Work | Q3: Other
A4: Date | B4: Source | C4: Category | D4: Cost | E4: Date | F4: Source | G4: Category | H4: Cost | I4: Date | J4: Source | K4: Category | L4: Cost | N4: Date | O4: Source | P4: Amount | Q4: Date | R4: Source | S4: Amount
A35: Total | D35: =SUM(D5:D34) -> 0 | E35: Total | H35: =SUM(H5:H34) -> 0 | I35: Total | L35: =SUBTOTAL(109,Sep!$L$5:$L$34) -> 0 | N35: Total | P35: =SUM(P5:P34) -> 0 | Q35: Total | S35: =SUM(S5:S34) -> 0
A37: Beg. Bal | C37: =Aug!S37 -> 650 | R37: End Bal. | S37: =C37+(P35+S35)-(D35+H35+L35) -> 650
A39: Amount Earned | B39: =P35+S35 -> 0 | O39: Public Transit | P39: Price | Q39: # Rides | R39: Cost
A40: Amount Spent | B40: =D35+H35+L35 -> 0 | O40: Subway/Bus | P40: 3 | Q40: 0 | R40: =P40*Q40 -> 0
A41: Remaining | B41: =B39-B40 -> 0 | O41: NJT | P41: 5.45 | Q41: 0 | R41: =P41*Q41 -> 0
O42: Jitney | P42: 3.5 | Q42: 0 | R42: =P42*Q42 -> 0
O43: Total | Q43: =SUBTOTAL(109,Q40:Q42) -> 0 | R43: =SUM(R40:R42) -> 0

Sheet Oct
A1: October
A2: Expenses | N2: Income
A3: Fixed | E3: Flexible | I3: Discretionary | N3: Work | Q3: Other
A4: Date | B4: Source | C4: Category | D4: Cost | E4: Date | F4: Source | G4: Category | H4: Cost | I4: Date | J4: Source | K4: Category | L4: Cost | N4: Date | O4: Source | P4: Amount | Q4: Date | R4: Source | S4: Amount
A35: Total | D35: =SUM(D5:D34) -> 0 | E35: Total | H35: =SUM(H5:H34) -> 0 | I35: Total | L35: =SUBTOTAL(109,Oct!$L$5:$L$34) -> 0 | N35: Total | P35: =SUM(P5:P34) -> 0 | Q35: Total | S35: =SUM(S5:S34) -> 0
A37: Beg. Bal | C37: =Sep!S37 -> 650 | R37: End Bal. | S37: =C37+(P35+S35)-(D35+H35+L35) -> 650
A39: Amount Earned | B39: =P35+S35 -> 0 | O39: Public Transit | P39: Price | Q39: # Rides | R39: Cost
A40: Amount Spent | B40: =D35+H35+L35 -> 0 | O40: Subway/Bus | P40: 3 | Q40: 0 | R40: =P40*Q40 -> 0
A41: Remaining | B41: =B39-B40 -> 0 | O41: NJT | P41: 5.45 | Q41: 0 | R41: =P41*Q41 -> 0
O42: Jitney | P42: 3.5 | Q42: 0 | R42: =P42*Q42 -> 0
O43: Total | Q43: =SUBTOTAL(109,Q40:Q42) -> 0 | R43: =SUM(R40:R42) -> 0

Sheet Nov
A1: November
A2: Expenses | N2: Income
A3: Fixed | E3: Flexible | I3: Discretionary | N3: Work | Q3: Other
A4: Date | B4: Source | C4: Category | D4: Cost | E4: Date | F4: Source | G4: Category | H4: Cost | I4: Date | J4: Source | K4: Category | L4: Cost | N4: Date | O4: Source | P4: Amount | Q4: Date | R4: Source | S4: Amount
A35: Total | D35: =SUM(D5:D34) -> 0 | E35: Total | H35: =SUM(H5:H34) -> 0 | I35: Total | L35: =SUBTOTAL(109,Nov!$L$5:$L$34) -> 0 | N35: Total | P35: =SUM(P5:P34) -> 0 | Q35: Total | S35: =SUM(S5:S34) -> 0
A37: Beg. Bal | C37: =Oct!S37 -> 650 | R37: End Bal. | S37: =C37+(P35+S35)-(D35+H35+L35) -> 650
A39: Amount Earned | B39: =P35+S35 -> 0 | O39: Public Transit | P39: Price | Q39: # Rides | R39: Cost
A40: Amount Spent | B40: =D35+H35+L35 -> 0 | O40: Subway/Bus | P40: 3 | Q40: 0 | R40: =P40*Q40 -> 0
A41: Remaining | B41: =B39-B40 -> 0 | O41: NJT | P41: 5.45 | Q41: 0 | R41: =P41*Q41 -> 0
O42: Jitney | P42: 3.5 | Q42: 0 | R42: =P42*Q42 -> 0
O43: Total | Q43: =SUBTOTAL(109,Q40:Q42) -> 0 | R43: =SUM(R40:R42) -> 0

Sheet Dec
A1: December
A2: Expenses | N2: Income
A3: Fixed | E3: Flexible | I3: Discretionary | N3: Work | Q3: Other
A4: Date | B4: Source | C4: Category | D4: Cost | E4: Date | F4: Source | G4: Category | H4: Cost | I4: Date | J4: Source | K4: Category | L4: Cost | N4: Date | O4: Source | P4: Amount | Q4: Date | R4: Source | S4: Amount
A35: Total | D35: =SUM(D5:D34) -> 0 | E35: Total | H35: =SUM(H5:H34) -> 0 | I35: Total | L35: =SUBTOTAL(109,Dec!$L$5:$L$34) -> 0 | N35: Total | P35: =SUM(P5:P34) -> 0 | Q35: Total | S35: =SUM(S5:S34) -> 0
A37: Beg. Bal | C37: =Nov!S37 -> 650 | R37: End Bal. | S37: =C37+(P35+S35)-(D35+H35+L35) -> 650
A39: Amount Earned | B39: =P35+S35 -> 0 | O39: Public Transit | P39: Price | Q39: # Rides | R39: Cost
A40: Amount Spent | B40: =D35+H35+L35 -> 0 | O40: Subway/Bus | P40: 3 | Q40: 0 | R40: =P40*Q40 -> 0
A41: Remaining | B41: =B39-B40 -> 0 | O41: NJT | P41: 5.45 | Q41: 0 | R41: =P41*Q41 -> 0
O42: Jitney | P42: 3.5 | Q42: 0 | R42: =P42*Q42 -> 0
O43: Total | Q43: =SUBTOTAL(109,Q40:Q42) -> 0 | R43: =SUM(R40:R42) -> 0

Sheet Totals
A1: Total Income
A2: This Year's Totals
A3: Income | B3: January | C3: February | D3: March | E3: April | F3: May | G3: June | H3: July | I3: August | J3: September | K3: October | L3: November | M3: December | N3: Total
A4: Work | B4: =Jan!$P$35 -> 5000 | C4: =Feb!$P$35 -> 0 | D4: =Mar!$P$35 -> 0 | E4: =Apr!$P$35 -> 0 | F4: =May!$P$35 -> 0 | G4: =Jun!$P$35 -> 0 | H4: =Jul!$P$35 -> 0 | I4: =Aug!$P$35 -> 0 | J4: =Sep!$P$35 -> 0 | K4: =Oct!$P$35 -> 0 | L4: =Nov!$P$35 -> 0 | M4: =Dec!$P$35 -> 0 | N4: =SUM(B4:M4) -> 5000
A5: Other | B5: =Jan!$S$35 -> 15 | C5: =Feb!$S$35 -> 0 | D5: =Mar!$S$35 -> 0 | E5: =Apr!$S$35 -> 0 | F5: =May!$S$35 -> 0 | G5: =Jun!$S$35 -> 0 | H5: =Jul!$S$35 -> 0 | I5: =Aug!$S$35 -> 0 | J5: =Sep!$S$35 -> 0 | K5: =Oct!$S$35 -> 0 | L5: =Nov!$S$35 -> 0 | M5: =Dec!$S$35 -> 0 | N5: =SUM(B5:M5) -> 15
A6: Total | B6: =SUM(B4:B5) -> 5015 | C6: =SUM(C4:C5) -> 0 | D6: =SUM(D4:D5) -> 0 | E6: =SUM(E4:E5) -> 0 | F6: =SUM(F4:F5) -> 0 | G6: =SUM(G4:G5) -> 0 | H6: =SUM(H4:H5) -> 0 | I6: =SUM(I4:I5) -> 0 | ... M6: =SUM(M4:M5) -> 0 | N6: =SUM(B6:M6) -> 5015
A8: Expenses | B8: =B3 -> January | C8: =C3 -> February | D8: =D3 -> March | E8: =E3 -> April | F8: =F3 -> May | G8: =G3 -> June | H8: =H3 -> July | I8: =I3 -> August | ... M8: =M3 -> December | N8: Total
A9: Fixed Expenses | B9: =Jan!$D$35 -> 4050 | C9: =Feb!$D$35 -> 0 | D9: =Mar!$D$35 -> 0 | E9: =Apr!$D$35 -> 0 | F9: =May!$D$35 -> 0 | G9: =Jun!$D$35 -> 0 | H9: =Jul!$D$35 -> 0 | I9: =Aug!$D$35 -> 0 | J9: =Sep!$D$35 -> 0 | K9: =Oct!$D$35 -> 0 | L9: =Nov!$D$35 -> 0 | M9: =Dec!$D$35 -> 0 | N9: =SUM(B9:M9) -> 4050
A10: Flexible Expenses | B10: =Jan!$H$35 -> 270 | C10: =Feb!$H$35 -> 0 | D10: =Mar!$H$35 -> 0 | E10: =Apr!$H$35 -> 0 | F10: =May!$H$35 -> 0 | G10: =Jun!$H$35 -> 0 | H10: =Jul!$H$35 -> 0 | I10: =Aug!$H$35 -> 0 | J10: =Sep!$H$35 -> 0 | K10: =Oct!$H$35 -> 0 | L10: =Nov!$H$35 -> 0 | M10: =Dec!$H$35 -> 0 | N10: =SUM(B10:M10) -> 270
A11: Discretionary Expenses | B11: =Jan!$L$35 -> 45 | C11: =Feb!$L$35 -> 0 | D11: =Mar!$L$35 -> 0 | E11: =Apr!$L$35 -> 0 | F11: =May!$L$35 -> 0 | G11: =Jun!$L$35 -> 0 | H11: =Jul!$L$35 -> 0 | I11: =Aug!$L$35 -> 0 | J11: =Sep!$L$35 -> 0 | K11: =Oct!$L$35 -> 0 | L11: =Nov!$L$35 -> 0 | M11: =Dec!$L$35 -> 0 | N11: =SUM(B11:M11) -> 45
A12: Total | B12: =SUM(B9:B11) -> 4365 | C12: =SUM(C9:C11) -> 0 | D12: =SUM(D9:D11) -> 0 | E12: =SUM(E9:E11) -> 0 | F12: =SUM(F9:F11) -> 0 | G12: =SUM(G9:G11) -> 0 | H12: =SUM(H9:H11) -> 0 | I12: =SUM(I9:I11) -> 0 | ... N12: =SUM(N9:N11) -> 4365
A14: Net | B14: =B6-B12 -> 650 | C14: =C6-C12 -> 0 | D14: =D6-D12 -> 0 | E14: =E6-E12 -> 0 | F14: =F6-F12 -> 0 | G14: =G6-G12 -> 0 | H14: =H6-H12 -> 0 | I14: =I6-I12 -> 0 | ... N14: =N6-N12 -> 650

Sheet Chart Data
B2: CHART DATA
B4: =MIN(1-B5,1) -> #REF!
B5: =MIN(Total_Monthly_Expenses/Total_Monthly_Income,1) -> #REF!
B6: =(Total_Monthly_Expenses/Total_Monthly_Income)>1 -> #REF!
